easypoint/__init__.py
easypoint/internal_types.py
easypoint/matrix.py
easypoint/point.py
easypoint/py.typed
easypoint/utils.py
easypoint-0.2.0.dist-info/LICENSE
easypoint-0.2.0.dist-info/METADATA
easypoint-0.2.0.dist-info/WHEEL
easypoint-0.2.0.dist-info/RECORD
