Metadata-Version: 2.1
Name: easypoint
Version: 0.2.0
Summary: Minimal general-purpose vector / matrix arithmetics library
License: MIT
Author: Dmitry Gritsenko
Author-email: k01419q45@ya.ru
Requires-Python: >=3.7,<4.0
Classifier: License :: OSI Approved :: MIT License
Classifier: Programming Language :: Python :: 3
Classifier: Programming Language :: Python :: 3.7
Classifier: Programming Language :: Python :: 3.8
Classifier: Programming Language :: Python :: 3.9
Classifier: Programming Language :: Python :: 3.10
Classifier: Programming Language :: Python :: 3.11
Requires-Dist: typing-extensions (>=4.7.1,<5.0.0)
